testkit_V2/__init__.py
AbdelrahmanReisha-0.1.1.dist-info/METADATA
AbdelrahmanReisha-0.1.1.dist-info/WHEEL
AbdelrahmanReisha-0.1.1.dist-info/top_level.txt
AbdelrahmanReisha-0.1.1.dist-info/RECORD
