Metadata-Version: 2.1
Name: AbdelrahmanReisha
Version: 0.1.1
Summary: basic data preprocessing package
Home-page: https://testwebsite.xyz
Author: AbdelrahmanReisha
Author-email: abdelrahmanrisha@gmail.com
License: The Unlicsense
Classifier: Development Status :: 3 - Alpha
Classifier: Intended Audience :: Developers
Classifier: Programming Language :: Python :: 3.11
Classifier: Topic :: Utilities
Requires-Python: >=3.11
Requires-Dist: requests
Requires-Dist: pandas >=2.0
